chalkboard/__init__.py
chalkboard/richtext.py
chalkboard-1.0.2.dist-info/METADATA
chalkboard-1.0.2.dist-info/WHEEL
chalkboard-1.0.2.dist-info/RECORD
