Metadata-Version: 2.3
Name: chalkboard
Version: 1.0.2
Summary: Text styling with many colors and effects
License: MIT
Author: Kyle Simpson
Author-email: Kyle_Simpson5624@yahoo.com
Requires-Python: >=3.8
Classifier: License :: OSI Approved :: MIT License
Classifier: Programming Language :: Python :: 3
Classifier: Programming Language :: Python :: 3.8
Classifier: Programming Language :: Python :: 3.9
Classifier: Programming Language :: Python :: 3.10
Classifier: Programming Language :: Python :: 3.11
Classifier: Programming Language :: Python :: 3.12
Classifier: Programming Language :: Python :: 3.13
